pycrc32-0.3.0.dist-info/METADATA
pycrc32-0.3.0.dist-info/WHEEL
pycrc32-0.3.0.dist-info/licenses/LICENSE.txt
pycrc32/tests/test_crc32.py
pycrc32/__init__.py
pycrc32/py.typed
pycrc32/pycrc32.cpython-313-arm-linux-gnueabihf.so
pycrc32-0.3.0.dist-info/RECORD
