Metadata-Version: 2.4
Name: pycrc32
Version: 0.3.0
Classifier: Programming Language :: Rust
Classifier: Programming Language :: Python
Classifier: Programming Language :: Python :: 3
Classifier: Programming Language :: Python :: 3 :: Only
Classifier: Programming Language :: Python :: 3.8
Classifier: Programming Language :: Python :: 3.9
Classifier: Programming Language :: Python :: 3.10
Classifier: Programming Language :: Python :: 3.11
Classifier: Programming Language :: Python :: 3.12
Classifier: License :: OSI Approved :: MIT License
Classifier: Operating System :: OS Independent
Classifier: Topic :: Scientific/Engineering
License-File: LICENSE.txt
Summary: Python module for SIMD-accelerated CRC32 checksum computation
Keywords: crc,crc32,simd,checksum
Home-Page: https://github.com/code-inflation/pycrc32
Author: cybuerg <robin.buergi@gmail.com>
Author-email: Robin Bürgi <robin.buergi@gmail.com>
License: MIT License
Requires-Python: >=3.8
Project-URL: Homepage, https://github.com/code-inflation/pycrc32
Project-URL: Repository, https://github.com/code-inflation/pycrc32
